torch_cif/__init__.py
torch_cif/cif.py
torch_cif-0.2.0.dist-info/LICENSE
torch_cif-0.2.0.dist-info/METADATA
torch_cif-0.2.0.dist-info/WHEEL
torch_cif-0.2.0.dist-info/top_level.txt
torch_cif-0.2.0.dist-info/RECORD
