Metadata-Version: 2.1
Name: torch-cif
Version: 0.2.0
Summary: A fast parallel implementation of continuous integrate-and-fire (CIF) https://arxiv.org/abs/1905.11235
Home-page: https://github.com/George0828Zhang/torch_cif
Author: Chih-Chiang Chang
Author-email: cc.chang0828@gmail.com
License: MIT
Keywords: speech speech-recognition asr automatic-speech-recognition speech-to-text speech-translation continuous-integrate-and-fire cif monotonic alignment torch pytorch
Classifier: Development Status :: 4 - Beta
Classifier: Intended Audience :: Developers
Classifier: Intended Audience :: Science/Research
Classifier: License :: OSI Approved :: MIT License
Classifier: Programming Language :: Python :: 3
Classifier: Programming Language :: Python :: 3 :: Only
Classifier: Programming Language :: Python :: 3.6
Classifier: Programming Language :: Python :: 3.7
Classifier: Programming Language :: Python :: 3.8
Classifier: Programming Language :: Python :: 3.9
Classifier: Programming Language :: Python :: 3.10
Classifier: Programming Language :: Python :: 3.11
Classifier: Programming Language :: Python :: 3.12
Classifier: Topic :: Scientific/Engineering :: Artificial Intelligence
Requires-Python: >=3.6
License-File: LICENSE
Requires-Dist: torch
Provides-Extra: test
Requires-Dist: hypothesis ; extra == 'test'
Requires-Dist: expecttest ; extra == 'test'
